ocr_bailian_mcp_server/__init__.py
ocr_bailian_mcp_server/server.py
ocr_bailian_mcp_server-0.1.0.dist-info/WHEEL
ocr_bailian_mcp_server-0.1.0.dist-info/entry_points.txt
ocr_bailian_mcp_server-0.1.0.dist-info/METADATA
ocr_bailian_mcp_server-0.1.0.dist-info/RECORD
