Metadata-Version: 2.3
Name: ocr-bailian-mcp-server
Version: 0.1.0
Summary: 用百炼视觉模型结构化提取身份证信息
Author: yangyang
Author-email: yangyang <2649233049@qq.com>
Requires-Dist: bs4>=0.0.2
Requires-Dist: dashscope>=1.25.10
Requires-Dist: dotenv>=0.9.9
Requires-Dist: httpx>=0.28.1
Requires-Dist: mcp[cli]>=1.26.0
Requires-Python: >=3.13
